findmyendpoints.py
models/NetworkInterface.py
models/__init__.py
models/bcolors.py
findmyendpoints-0.9.dist-info/LICENSE
findmyendpoints-0.9.dist-info/METADATA
findmyendpoints-0.9.dist-info/WHEEL
findmyendpoints-0.9.dist-info/top_level.txt
findmyendpoints-0.9.dist-info/RECORD
