Metadata-Version: 2.1
Name: findmyendpoints
Version: 0.9
Summary: This tool will find and display information about public endpoints in an AWS account
Author-email: Jeff Maley <jeffmaley@gmail.com>
License: # MIT License
Project-URL: Homepage, https://github.com/jeffmaley/findmyendpoints
Project-URL: Bug Tracker, https://github.com/jeffmaley/findmyendpoints/issues
Classifier: Programming Language :: Python :: 3
Classifier: License :: OSI Approved :: MIT License
Classifier: Operating System :: OS Independent
Requires-Python: >=3.7
License-File: LICENSE
